the_garden/__init__.py
the_garden/__main__.py
the_garden/garden_params.py
the_garden/the_garden_main.py
kabbes_the_garden-0.3.0.dist-info/LICENSE
kabbes_the_garden-0.3.0.dist-info/METADATA
kabbes_the_garden-0.3.0.dist-info/WHEEL
kabbes_the_garden-0.3.0.dist-info/top_level.txt
kabbes_the_garden-0.3.0.dist-info/RECORD
